setup.py
CreateAppendGet/CAG.py
CreateAppendGet/__init__.py
CreateAppendGet.egg-info/PKG-INFO
CreateAppendGet.egg-info/SOURCES.txt
CreateAppendGet.egg-info/dependency_links.txt
CreateAppendGet.egg-info/entry_points.txt
CreateAppendGet.egg-info/not-zip-safe
CreateAppendGet.egg-info/requires.txt
CreateAppendGet.egg-info/top_level.txt