Metadata-Version: 1.0
Name: CreateAppendGet
Version: 1.0
Summary: Library for ZODB-based storage and retrival of many, many small objects
Home-page: http://www.nidelven-it.no/d
Author: Morten W. Petersen
Author-email: info@nidelven-it.no
License: ZPL 2.1
Keywords: python zodb zope plone silva library storage database
Platform: UNKNOWN
Classifier: Programming Language :: Python
Classifier: Framework :: ZODB
Classifier: Framework :: Zope2
Classifier: License :: OSI Approved :: Zope Public License
Classifier: Operating System :: OS Independent
